ALU.v
module ALU(
    input [31:0] left,
    input [31:0] right,
    input [3:0] control, 
    output [31:0] out
);

always @(left, right, control)
    begin
       case(control)
        4'b0000: out = left & right; 
        4'b0001: out = left | right; // hello
        4'b0010: out = left + right; 
        4'b0110: out = left - right; 
        4'b0111: out = left < right; 
        4'b1100: out = left ~| right; 
       endcase
    end   
endmodule

modules/ram.v
`timescale 1 ns / 1 ps

module single_port_sync_ram
    # ( parameter ADDR_WIDTH = 28, // Adjusted address width
        parameter DATA_WIDTH = 8,  // Adjusted data width
        parameter LENGTH = (1<<ADDR_WIDTH)
    )
  (   input clk,
      inout [ADDR_WIDTH-1:0] addr,  // Adjusted address width
      inout [DATA_WIDTH-1:0] data,  // Adjusted data width
      input cs,
      input we,
      input oe
  );

  reg [DATA_WIDTH-1:0] tmp_data;
  reg [DATA_WIDTH-1:0] mem[LENGTH]; // 1 << 30 = 60

  always @ (posedge clk) begin
    if (cs & we)
      mem[addr] <= data;
  end
  
  always @ (negedge clk) begin
    if (cs & !we)
      tmp_data <= mem[addr];
  end

  assign data = cs & oe & !we ? tmp_data : 'hz;
endmodule

modules/decoder.v
// Adopted from https://circuitcove.com/design-examples-decoders/
`timescale 1 ns / 1 ps


module decoder
  # (parameter ENCODE_WIDTH = 2,
     parameter DECODE_WIDTH = 2**ENCODE_WIDTH
    )

  (
    input  [ENCODE_WIDTH-1:0] in,
    output [DECODE_WIDTH-1:0] out
  );

  localparam latency = 1;

  assign #latency out = 'b1<<in;

endmodule

modules/ram_large.v
`timescale 1 ns / 1 ps

module single_port_sync_ram_large
  # ( parameter ADDR_WIDTH = 30,  // Updated address width for 1 GiB
      parameter DATA_WIDTH = 32,  // Data width remains 32 bits
      parameter DATA_WIDTH_SHIFT = 2  // Log base 2 of 4, since we're using 4 modules
    )
  (   input clk,
      input [ADDR_WIDTH-1:0] addr,
      inout [DATA_WIDTH-1:0] data,
      input cs_input,
      input we,
      input oe
  );

  wire [1:0] cs;  // Only 2 bits needed now, for 4 modules

  // Updated decoder for 2-bit output
  decoder #(.ENCODE_WIDTH(2)) dec
  (   .in(addr[ADDR_WIDTH-1:ADDR_WIDTH-2]),
      .out(cs) 
  );

  // Four instances of the smaller RAM module
  single_port_sync_ram  #(.DATA_WIDTH(DATA_WIDTH/2)) u00
  (   .clk(clk),
      .addr(addr[ADDR_WIDTH-3:0]),
      .data(data[(DATA_WIDTH>>DATA_WIDTH_SHIFT)-1:0]),
      .cs(cs[0]),
      .we(we),
      .oe(oe)
  );
  single_port_sync_ram #(.DATA_WIDTH(DATA_WIDTH>>DATA_WIDTH_SHIFT)) u01
  (   .clk(clk),
      .addr(addr[ADDR_WIDTH-3:0]),
      .data(data[DATA_WIDTH-1:DATA_WIDTH>>DATA_WIDTH_SHIFT]),
      .cs(cs[0]),
      .we(we),
      .oe(oe)
  );

  single_port_sync_ram  #(.DATA_WIDTH(DATA_WIDTH/2)) u10
  (   .clk(clk),
      .addr(addr[ADDR_WIDTH-3:0]),
      .data(data[(DATA_WIDTH>>DATA_WIDTH_SHIFT)-1:0]),
      .cs(cs[1]),
      .we(we),
      .oe(oe)
  );
  single_port_sync_ram #(.DATA_WIDTH(DATA_WIDTH>>DATA_WIDTH_SHIFT)) u11
  (   .clk(clk),
      .addr(addr[ADDR_WIDTH-3:0]),
      .data(data[DATA_WIDTH-1:DATA_WIDTH>>DATA_WIDTH_SHIFT]),
      .cs(cs[1]),
      .we(we),
      .oe(oe)
  );

endmodule

tests/cpu_test.v
`include "modules/alu.v"
`include "modules/ram.v"
`include "modules/ram_large.v"
`include "modules/decoder.v"

`timescale 1 ns / 1 ps

module test_cpu;
    parameter ADDR_WIDTH = 28;
    parameter DATA_WIDTH = 32;
    
    reg osc;
    localparam period = 10;
    
    wire clock;
    assign clk = osc;

    reg cs; // chip select
    reg we; // write enable
    reg oe; // out enable
    integer i;
    reg [ADDR_WIDTH-1:0] MAR;
    wire [DATA_WIDTH-1:0] data;
    reg [DATA_WIDTH-1:0] testbench_data;
    assign data = !oe ? testbench_data : 'hz;

    single_port_sync_ram_large #(.DATA_WIDTH(DATA_WIDTH)) ram(
    .clk(clock),
    .addr(MAR),
    .data(data[DATA_WIDTH-1:0]),
    .cs_input(cs),
    .we(we),
    .oe(oe)
    );

    reg [31:0] left;
    reg [31:0] right;
    wire [31:0] alu_out;
    reg [3:0] alu_select;

    alu alu32(
    .left(left),
    .right(right), // 32-bit ALU inputs
    .control(alu_select), // 4-bit ALU mode select
    .out(alu_out) // 32-bit ALU output
    );

    // Maybe initialize PC here
    reg[31:0] PC;

    reg [31:0] program_counter = 'h100;
    reg [31:0] instruction_register = 'h0;
    reg [31:0] memory_buffer_register = 'h0;
    reg [31:0] AC = 'h0; // initialize accumulator here and delete this

    initial osc = 1; // don't quite understand this part (clocks stuff & needs to be changed)
    always begin
        #period osc = ~osc;
    end
    initial begin
    $dumpfile("dump.vcd");// imagine using dump 0-0
    $dumpvars;

    // Fibonnaci sequence program

    @(posedge clock) MAR <= 'h0000100; we <= 1; cs <= 1; oe <= 0; testbench_data <= 'h20000113;
    @(posedge clock) MAR <= 'h0000101; we <= 1; cs <= 1; oe <= 0; testbench_data <= 'h00000111;
    @(posedge clock) MAR <= 'h0000102; we <= 1; cs <= 1; oe <= 0; testbench_data <= 'h30000113;
    @(posedge clock) MAR <= 'h0000103; we <= 1; cs <= 1; oe <= 0; testbench_data <= 'h20000111;
    @(posedge clock) MAR <= 'h0000104; we <= 1; cs <= 1; oe <= 0; testbench_data <= 'h30000112;
    @(posedge clock) MAR <= 'h0000105; we <= 1; cs <= 1; oe <= 0; testbench_data <= 'h20000113;
    @(posedge clock) MAR <= 'h0000106; we <= 1; cs <= 1; oe <= 0; testbench_data <= 'h00000112;
    @(posedge clock) MAR <= 'h0000107; we <= 1; cs <= 1; oe <= 0; testbench_data <= 'h30000113;
    @(posedge clock) MAR <= 'h0000108; we <= 1; cs <= 1; oe <= 0; testbench_data <= 'h20000112;
    @(posedge clock) MAR <= 'h0000109; we <= 1; cs <= 1; oe <= 0; testbench_data <= 'h30000113;
    @(posedge clock) MAR <= 'h000010A; we <= 1; cs <= 1; oe <= 0; testbench_data <= 'h20000114;
    @(posedge clock) MAR <= 'h000010B; we <= 1; cs <= 1; oe <= 0; testbench_data <= 'h00000115;
    @(posedge clock) MAR <= 'h000010C; we <= 1; cs <= 1; oe <= 0; testbench_data <= 'h30000114;
    @(posedge clock) MAR <= 'h000010D; we <= 1; cs <= 1; oe <= 0; testbench_data <= 'h20000114;
    @(posedge clock) MAR <= 'h000010E; we <= 1; cs <= 1; oe <= 0; testbench_data <= 'h50000002;
    @(posedge clock) MAR <= 'h000010F; we <= 1; cs <= 1; oe <= 0; testbench_data <= 'h60000100;
    @(posedge clock) MAR <= 'h0000110; we <= 1; cs <= 1; oe <= 0; testbench_data <= 'h10000000;
    @(posedge clock) MAR <= 'h0000111; we <= 1; cs <= 1; oe <= 0; testbench_data <= 'd0;
    @(posedge clock) MAR <= 'h0000112; we <= 1; cs <= 1; oe <= 0; testbench_data <= 'd1;
    @(posedge clock) MAR <= 'h0000113; we <= 1; cs <= 1; oe <= 0; testbench_data <= 'd0;
    @(posedge clock) MAR <= 'h0000114; we <= 1; cs <= 1; oe <= 0; testbench_data <= 'd10;
    @(posedge clock) MAR <= 'h0000115; we <= 1; cs <= 1; oe <= 0; testbench_data <= 'hFFFFFFFF;

    @(posedge clock) PC <= 'h100;

    for (i = 0; i < 128; i = i + 1) begin
        // fetch
        @(posedge clock) MAR <= program_counter; we <= 0;
        cs <= 1;
        oe <= 1;
        @(posedge clock) instruction_register <= data;
        @(posedge clock) program_counter = program_counter + 1;

        // decode & execute

        case(instruction_register[31:28]) // first 4 bits
        4'b0000: begin // ADD
            @(posedge clock) MAR <= instruction_register[27:0];
            @(posedge clock) memory_buffer_register <= data;
            @(posedge clock) alu_select <= 'b0010; left <= AC; right <= memory_buffer_register;
            @(posedge clock) AC <= alu_out;
        end
        4'b0001: begin // HALT
            @(posedge clock) PC <= PC - 1;
        end
        4'b0010: begin // LOAD WORD
            @(posedge clock) MAR <= instruction_register[27:0];
            @(posedge clock) memory_buffer_register <= data;
            @(posedge clock) AC <= memory_buffer_register;
        end
        4'b0011: begin // STORE WORD
            @(posedge clock) MAR <= instruction_register[27:0];
            @(posedge clock) memory_buffer_register <= AC;
            @(posedge clock) we <= 1; oe <= 0; testbench_data <= memory_buffer_register;
        end
        4'b0100: begin // CLEAR
            @(posedge clock) AC <= 0;
        end
        4'b0101: begin // SKIP
            @(posedge clock) if(instruction_register[2:0] == 3'b010 && AC == 0) PC <= PC + 1;
            else if (instruction_register[2:0] == 3'b000 && AC < 0) PC <= PC + 1;
            else if (instruction_register[2:0] == 3'b100 && AC > 0) PC <= PC + 1;
        end
        4'b0110: begin // JUMP
            @(posedge clock) PC <= instruction_register[27:0];
        end
        4'b0111: begin // ADDI (4 bit immediate value)
            @(posedge clock) memory_buffer_register <= data;
            @(posedge clock) alu_select <= 'b0010; left <= AC; right <= instruction_register[27:20];
            @(posedge clock)AC <= alu_out;
        end
	endcase
end
@(posedge clock) MAR <= 'h10D; we <= 0; cs <= 1; oe <= 1;
@(posedge clock)

#20 $finish;
end
endmodule

dump.vcd
$date
	Sat Dec  9 02:19:32 2023
$end
$version
	Icarus Verilog
$end
$timescale
	1ps
$end
$scope module test_cpu $end
$var wire 1 ! clock $end
$var wire 32 " data [31:0] $end
$var wire 32 # alu_out [31:0] $end
$var reg 32 $ AC [31:0] $end
$var reg 28 % MAR [27:0] $end
$var reg 32 & PC [31:0] $end
$var reg 4 ' alu_select [3:0] $end
$var reg 1 ( cs $end
$var reg 32 ) instruction_register [31:0] $end
$var reg 32 * left [31:0] $end
$var reg 32 + memory_buffer_register [31:0] $end
$var reg 1 , oe $end
$var reg 1 - osc $end
$var reg 32 . program_counter [31:0] $end
$var reg 32 / right [31:0] $end
$var reg 32 0 testbench_data [31:0] $end
$var reg 1 1 we $end
$var integer 32 2 i [31:0] $end
$scope module alu32 $end
$var wire 4 3 control [3:0] $end
$var wire 32 4 left [31:0] $end
$var wire 32 5 right [31:0] $end
$var reg 32 6 out [31:0] $end
$upscope $end
$scope module ram $end
$var wire 28 7 addr [27:0] $end
$var wire 1 ! clk $end
$var wire 1 ( cs_input $end
$var wire 32 8 data [31:0] $end
$var wire 1 , oe $end
$var wire 1 1 we $end
$var wire 2 9 cs [1:0] $end
$scope module dec $end
$var wire 1 : in $end
$var wire 2 ; out [1:0] $end
$upscope $end
$scope module u00 $end
$var wire 26 < addr [25:0] $end
$var wire 1 ! clk $end
$var wire 1 = cs $end
$var wire 16 > data [15:0] $end
$var wire 1 , oe $end
$var wire 1 1 we $end
$var reg 16 ? tmp_data [15:0] $end
$upscope $end
$scope module u01 $end
$var wire 26 @ addr [25:0] $end
$var wire 1 ! clk $end
$var wire 1 A cs $end
$var wire 16 B data [15:0] $end
$var wire 1 , oe $end
$var wire 1 1 we $end
$var reg 16 C tmp_data [15:0] $end
$upscope $end
$scope module u10 $end
$var wire 26 D addr [25:0] $end
$var wire 1 ! clk $end
$var wire 1 E cs $end
$var wire 16 F data [15:0] $end
$var wire 1 , oe $end
$var wire 1 1 we $end
$var reg 16 G tmp_data [15:0] $end
$upscope $end
$scope module u11 $end
$var wire 26 H addr [25:0] $end
$var wire 1 ! clk $end
$var wire 1 I cs $end
$var wire 16 J data [15:0] $end
$var wire 1 , oe $end
$var wire 1 1 we $end
$var reg 16 K tmp_data [15:0] $end
$upscope $end
$upscope $end
$upscope $end
$enddefinitions $end
#0
$dumpvars
bx K
bx J
xI
bx H
bx G
bx F
xE
bx D
bx C
bx B
xA
bx @
bx ?
bx >
x=
bx <
bx ;
x:
bx 9
bx 8
bx 7
bx 6
bx 5
bx 4
bx 3
bx 2
x1
bx 0
bx /
b100000000 .
1-
x,
b0 +
bx *
b0 )
x(
bx '
bx &
bx %
b0 $
bx #
bx "
1!
$end
#10000
0!
0-
#20000
b100010011 >
b10000000000000 B
b100010011 F
b10000000000000 J
b100000000000000000000100010011 "
b100000000000000000000100010011 8
0:
b100000000 <
b100000000 @
b100000000 D
b100000000 H
b100000000 7
b100000000000000000000100010011 0
0,
1(
11
b100000000 %
1!
1-
#21000
0I
0E
1A
1=
b1 9
b1 ;
#30000
0!
0-
#40000
b100010001 >
b0 B
b100010001 F
b0 J
b100010001 "
b100010001 8
b100000001 <
b100000001 @
b100000001 D
b100000001 H
b100000001 7
b100010001 0
b100000001 %
1!
1-
#50000
0!
0-
#60000
b100010011 >
b11000000000000 B
b100010011 F
b11000000000000 J
b110000000000000000000100010011 "
b110000000000000000000100010011 8
b100000010 <
b100000010 @
b100000010 D
b100000010 H
b100000010 7
b110000000000000000000100010011 0
b100000010 %
1!
1-
#70000
0!
0-
#80000
b100010001 >
b10000000000000 B
b100010001 F
b10000000000000 J
b100000000000000000000100010001 "
b100000000000000000000100010001 8
b100000011 <
b100000011 @
b100000011 D
b100000011 H
b100000011 7
b100000000000000000000100010001 0
b100000011 %
1!
1-
#90000
0!
0-
#100000
b100010010 >
b11000000000000 B
b100010010 F
b11000000000000 J
b110000000000000000000100010010 "
b110000000000000000000100010010 8
b100000100 <
b100000100 @
b100000100 D
b100000100 H
b100000100 7
b110000000000000000000100010010 0
b100000100 %
1!
1-
#110000
0!
0-
#120000
b100010011 >
b10000000000000 B
b100010011 F
b10000000000000 J
b100000000000000000000100010011 "
b100000000000000000000100010011 8
b100000101 <
b100000101 @
b100000101 D
b100000101 H
b100000101 7
b100000000000000000000100010011 0
b100000101 %
1!
1-
#130000
0!
0-
#140000
b100010010 >
b0 B
b100010010 F
b0 J
b100010010 "
b100010010 8
b100000110 <
b100000110 @
b100000110 D
b100000110 H
b100000110 7
b100010010 0
b100000110 %
1!
1-
#150000
0!
0-
#160000
b100010011 >
b11000000000000 B
b100010011 F
b11000000000000 J
b110000000000000000000100010011 "
b110000000000000000000100010011 8
b100000111 <
b100000111 @
b100000111 D
b100000111 H
b100000111 7
b110000000000000000000100010011 0
b100000111 %
1!
1-
#170000
0!
0-
#180000
b100010010 >
b10000000000000 B
b100010010 F
b10000000000000 J
b100000000000000000000100010010 "
b100000000000000000000100010010 8
b100001000 <
b100001000 @
b100001000 D
b100001000 H
b100001000 7
b100000000000000000000100010010 0
b100001000 %
1!
1-
#190000
0!
0-
#200000
b100010011 >
b11000000000000 B
b100010011 F
b11000000000000 J
b110000000000000000000100010011 "
b110000000000000000000100010011 8
b100001001 <
b100001001 @
b100001001 D
b100001001 H
b100001001 7
b110000000000000000000100010011 0
b100001001 %
1!
1-
#210000
0!
0-
#220000
b100010100 >
b10000000000000 B
b100010100 F
b10000000000000 J
b100000000000000000000100010100 "
b100000000000000000000100010100 8
b100001010 <
b100001010 @
b100001010 D
b100001010 H
b100001010 7
b100000000000000000000100010100 0
b100001010 %
1!
1-
#230000
0!
0-
#240000
b100010101 >
b0 B
b100010101 F
b0 J
b100010101 "
b100010101 8
b100001011 <
b100001011 @
b100001011 D
b100001011 H
b100001011 7
b100010101 0
b100001011 %
1!
1-
#250000
0!
0-
#260000
b100010100 >
b11000000000000 B
b100010100 F
b11000000000000 J
b110000000000000000000100010100 "
b110000000000000000000100010100 8
b100001100 <
b100001100 @
b100001100 D
b100001100 H
b100001100 7
b110000000000000000000100010100 0
b100001100 %
1!
1-
#270000
0!
0-
#280000
b10000000000000 B
b10000000000000 J
b100000000000000000000100010100 "
b100000000000000000000100010100 8
b100001101 <
b100001101 @
b100001101 D
b100001101 H
b100001101 7
b100000000000000000000100010100 0
b100001101 %
1!
1-
#290000
0!
0-
#300000
b10 >
b101000000000000 B
b10 F
b101000000000000 J
b1010000000000000000000000000010 "
b1010000000000000000000000000010 8
b100001110 <
b100001110 @
b100001110 D
b100001110 H
b100001110 7
b1010000000000000000000000000010 0
b100001110 %
1!
1-
#310000
0!
0-
#320000
b100000000 >
b110000000000000 B
b100000000 F
b110000000000000 J
b1100000000000000000000100000000 "
b1100000000000000000000100000000 8
b100001111 <
b100001111 @
b100001111 D
b100001111 H
b100001111 7
b1100000000000000000000100000000 0
b100001111 %
1!
1-
#330000
0!
0-
#340000
b0 >
b1000000000000 B
b0 F
b1000000000000 J
b10000000000000000000000000000 "
b10000000000000000000000000000 8
b100010000 <
b100010000 @
b100010000 D
b100010000 H
b100010000 7
b10000000000000000000000000000 0
b100010000 %
1!
1-
#350000
0!
0-
#360000
b0 B
b0 J
b0 "
b0 8
b100010001 <
b100010001 @
b100010001 D
b100010001 H
b100010001 7
b0 0
b100010001 %
1!
1-
#370000
0!
0-
#380000
b1 >
b1 F
b1 "
b1 8
b100010010 <
b100010010 @
b100010010 D
b100010010 H
b100010010 7
b1 0
b100010010 %
1!
1-
#390000
0!
0-
#400000
b0 >
b0 F
b0 "
b0 8
b100010011 <
b100010011 @
b100010011 D
b100010011 H
b100010011 7
b0 0
b100010011 %
1!
1-
#410000
0!
0-
#420000
b1010 >
b1010 F
b1010 "
b1010 8
b100010100 <
b100010100 @
b100010100 D
b100010100 H
b100010100 7
b1010 0
b100010100 %
1!
1-
#430000
0!
0-
#440000
b1111111111111111 >
b1111111111111111 B
b1111111111111111 F
b1111111111111111 J
b11111111111111111111111111111111 "
b11111111111111111111111111111111 8
b100010101 <
b100010101 @
b100010101 D
b100010101 H
b100010101 7
b11111111111111111111111111111111 0
b100010101 %
1!
1-
#450000
0!
0-
#460000
b100000000 &
b0 2
1!
1-
#470000
0!
0-
#480000
bx >
bx B
bx F
bx J
bx "
bx 8
b100000000 <
b100000000 @
b100000000 D
b100000000 H
b100000000 7
1,
01
b100000000 %
1!
1-
#490000
b100010011 >
b10000000000000 B
b100010011 F
b10000000000000 J
b100000000000000000000100010011 "
b100000000000000000000100010011 8
b100010011 ?
b10000000000000 C
0!
0-
#500000
b100000000000000000000100010011 )
1!
1-
#510000
0!
0-
#520000
b100000001 .
1!
1-
#530000
0!
0-
#540000
b100010011 <
b100010011 @
b100010011 D
b100010011 H
b100010011 7
b100010011 %
1!
1-
#550000
b0 >
b0 B
b0 F
b0 J
b0 "
b0 8
b0 C
b0 ?
0!
0-
#560000
1!
1-
#570000
0!
0-
#580000
b1 2
1!
1-
#590000
0!
0-
#600000
b100000001 <
b100000001 @
b100000001 D
b100000001 H
b100000001 7
b100000001 %
1!
1-
#610000
b100010001 >
b100010001 F
b100010001 "
b100010001 8
b100010001 ?
0!
0-
#620000
b100010001 )
1!
1-
#630000
0!
0-
#640000
b100000010 .
1!
1-
#650000
0!
0-
#660000
b100010001 <
b100010001 @
b100010001 D
b100010001 H
b100010001 7
b100010001 %
1!
1-
#670000
b0 >
b0 F
b0 "
b0 8
b0 ?
0!
0-
#680000
1!
1-
#690000
0!
0-
#700000
b0 #
b0 6
b0 /
b0 5
b0 *
b0 4
b10 '
b10 3
1!
1-
#710000
0!
0-
#720000
b10 2
1!
1-
#730000
0!
0-
#740000
b100000010 <
b100000010 @
b100000010 D
b100000010 H
b100000010 7
b100000010 %
1!
1-
#750000
b100010011 >
b11000000000000 B
b100010011 F
b11000000000000 J
b110000000000000000000100010011 "
b110000000000000000000100010011 8
b11000000000000 C
b100010011 ?
0!
0-
#760000
b110000000000000000000100010011 )
1!
1-
#770000
0!
0-
#780000
b100000011 .
1!
1-
#790000
0!
0-
#800000
b100010011 <
b100010011 @
b100010011 D
b100010011 H
b100010011 7
b100010011 %
1!
1-
#810000
b0 >
b0 B
b0 F
b0 J
b0 "
b0 8
b0 ?
b0 C
0!
0-
#820000
1!
1-
#830000
0!
0-
#840000
b0 0
0,
11
b11 2
1!
1-
#850000
0!
0-
#860000
b0 >
b0 B
b0 F
b0 J
b0 "
b0 8
b100000011 <
b100000011 @
b100000011 D
b100000011 H
b100000011 7
1,
01
b100000011 %
1!
1-
#870000
b100010001 >
b10000000000000 B
b100010001 F
b10000000000000 J
b100000000000000000000100010001 "
b100000000000000000000100010001 8
b10000000000000 C
b100010001 ?
0!
0-
#880000
b100000000000000000000100010001 )
1!
1-
#890000
0!
0-
#900000
b100000100 .
1!
1-
#910000
0!
0-
#920000
b100010001 <
b100010001 @
b100010001 D
b100010001 H
b100010001 7
b100010001 %
1!
1-
#930000
b0 >
b0 B
b0 F
b0 J
b0 "
b0 8
b0 ?
b0 C
0!
0-
#940000
1!
1-
#950000
0!
0-
#960000
b100 2
1!
1-
#970000
0!
0-
#980000
b100000100 <
b100000100 @
b100000100 D
b100000100 H
b100000100 7
b100000100 %
1!
1-
#990000
b100010010 >
b11000000000000 B
b100010010 F
b11000000000000 J
b110000000000000000000100010010 "
b110000000000000000000100010010 8
b11000000000000 C
b100010010 ?
0!
0-
#1000000
b110000000000000000000100010010 )
1!
1-
#1010000
0!
0-
#1020000
b100000101 .
1!
1-
#1030000
0!
0-
#1040000
b100010010 <
b100010010 @
b100010010 D
b100010010 H
b100010010 7
b100010010 %
1!
1-
#1050000
b1 >
b0 B
b1 F
b0 J
b1 "
b1 8
b1 ?
b0 C
0!
0-
#1060000
1!
1-
#1070000
0!
0-
#1080000
b0 >
b0 F
b0 "
b0 8
0,
11
b101 2
1!
1-
#1090000
0!
0-
#1100000
b1 >
b0 B
b1 F
b0 J
b1 "
b1 8
b100000101 <
b100000101 @
b100000101 D
b100000101 H
b100000101 7
1,
01
b100000101 %
1!
1-
#1110000
b100010011 >
b10000000000000 B
b100010011 F
b10000000000000 J
b100000000000000000000100010011 "
b100000000000000000000100010011 8
b10000000000000 C
b100010011 ?
0!
0-
#1120000
b100000000000000000000100010011 )
1!
1-
#1130000
0!
0-
#1140000
b100000110 .
1!
1-
#1150000
0!
0-
#1160000
b100010011 <
b100010011 @
b100010011 D
b100010011 H
b100010011 7
b100010011 %
1!
1-
#1170000
b0 >
b0 B
b0 F
b0 J
b0 "
b0 8
b0 ?
b0 C
0!
0-
#1180000
1!
1-
#1190000
0!
0-
#1200000
b110 2
1!
1-
#1210000
0!
0-
#1220000
b100000110 <
b100000110 @
b100000110 D
b100000110 H
b100000110 7
b100000110 %
1!
1-
#1230000
b100010010 >
b100010010 F
b100010010 "
b100010010 8
b100010010 ?
0!
0-
#1240000
b100010010 )
1!
1-
#1250000
0!
0-
#1260000
b100000111 .
1!
1-
#1270000
0!
0-
#1280000
b100010010 <
b100010010 @
b100010010 D
b100010010 H
b100010010 7
b100010010 %
1!
1-
#1290000
b0 >
b0 F
b0 "
b0 8
b0 ?
0!
0-
#1300000
1!
1-
#1310000
0!
0-
#1320000
1!
1-
#1330000
0!
0-
#1340000
b111 2
1!
1-
#1350000
0!
0-
#1360000
b100000111 <
b100000111 @
b100000111 D
b100000111 H
b100000111 7
b100000111 %
1!
1-
#1370000
b100010011 >
b11000000000000 B
b100010011 F
b11000000000000 J
b110000000000000000000100010011 "
b110000000000000000000100010011 8
b100010011 ?
b11000000000000 C
0!
0-
#1380000
b110000000000000000000100010011 )
1!
1-
#1390000
0!
0-
#1400000
b100001000 .
1!
1-
#1410000
0!
0-
#1420000
b100010011 <
b100010011 @
b100010011 D
b100010011 H
b100010011 7
b100010011 %
1!
1-
#1430000
b0 >
b0 B
b0 F
b0 J
b0 "
b0 8
b0 C
b0 ?
0!
0-
#1440000
1!
1-
#1450000
0!
0-
#1460000
0,
11
b1000 2
1!
1-
#1470000
0!
0-
#1480000
b0 >
b0 B
b0 F
b0 J
b0 "
b0 8
b100001000 <
b100001000 @
b100001000 D
b100001000 H
b100001000 7
1,
01
b100001000 %
1!
1-
#1490000
b100010010 >
b10000000000000 B
b100010010 F
b10000000000000 J
b100000000000000000000100010010 "
b100000000000000000000100010010 8
b100010010 ?
b10000000000000 C
0!
0-
#1500000
b100000000000000000000100010010 )
1!
1-
#1510000
0!
0-
#1520000
b100001001 .
1!
1-
#1530000
0!
0-
#1540000
b100010010 <
b100010010 @
b100010010 D
b100010010 H
b100010010 7
b100010010 %
1!
1-
#1550000
b0 >
b0 B
b0 F
b0 J
b0 "
b0 8
b0 C
b0 ?
0!
0-
#1560000
1!
1-
#1570000
0!
0-
#1580000
b1001 2
1!
1-
#1590000
0!
0-
#1600000
b100001001 <
b100001001 @
b100001001 D
b100001001 H
b100001001 7
b100001001 %
1!
1-
#1610000
b100010011 >
b11000000000000 B
b100010011 F
b11000000000000 J
b110000000000000000000100010011 "
b110000000000000000000100010011 8
b100010011 ?
b11000000000000 C
0!
0-
#1620000
b110000000000000000000100010011 )
1!
1-
#1630000
0!
0-
#1640000
b100001010 .
1!
1-
#1650000
0!
0-
#1660000
b100010011 <
b100010011 @
b100010011 D
b100010011 H
b100010011 7
b100010011 %
1!
1-
#1670000
b0 >
b0 B
b0 F
b0 J
b0 "
b0 8
b0 C
b0 ?
0!
0-
#1680000
1!
1-
#1690000
0!
0-
#1700000
0,
11
b1010 2
1!
1-
#1710000
0!
0-
#1720000
b0 >
b0 B
b0 F
b0 J
b0 "
b0 8
b100001010 <
b100001010 @
b100001010 D
b100001010 H
b100001010 7
1,
01
b100001010 %
1!
1-
#1730000
b100010100 >
b10000000000000 B
b100010100 F
b10000000000000 J
b100000000000000000000100010100 "
b100000000000000000000100010100 8
b100010100 ?
b10000000000000 C
0!
0-
#1740000
b100000000000000000000100010100 )
1!
1-
#1750000
0!
0-
#1760000
b100001011 .
1!
1-
#1770000
0!
0-
#1780000
b100010100 <
b100010100 @
b100010100 D
b100010100 H
b100010100 7
b100010100 %
1!
1-
#1790000
b1010 >
b0 B
b1010 F
b0 J
b1010 "
b1010 8
b0 C
b1010 ?
0!
0-
#1800000
b1010 +
1!
1-
#1810000
0!
0-
#1820000
b1010 $
b1011 2
1!
1-
#1830000
0!
0-
#1840000
b100001011 <
b100001011 @
b100001011 D
b100001011 H
b100001011 7
b100001011 %
1!
1-
#1850000
b100010101 >
b100010101 F
b100010101 "
b100010101 8
b100010101 ?
0!
0-
#1860000
b100010101 )
1!
1-
#1870000
0!
0-
#1880000
b100001100 .
1!
1-
#1890000
0!
0-
#1900000
b100010101 <
b100010101 @
b100010101 D
b100010101 H
b100010101 7
b100010101 %
1!
1-
#1910000
b1111111111111111 >
b1111111111111111 B
b1111111111111111 F
b1111111111111111 J
b11111111111111111111111111111111 "
b11111111111111111111111111111111 8
b1111111111111111 C
b1111111111111111 ?
0!
0-
#1920000
b11111111111111111111111111111111 +
1!
1-
#1930000
0!
0-
#1940000
b1001 #
b1001 6
b11111111111111111111111111111111 /
b11111111111111111111111111111111 5
b1010 *
b1010 4
1!
1-
#1950000
0!
0-
#1960000
b1001 $
b1100 2
1!
1-
#1970000
0!
0-
#1980000
b100001100 <
b100001100 @
b100001100 D
b100001100 H
b100001100 7
b100001100 %
1!
1-
#1990000
b100010100 >
b11000000000000 B
b100010100 F
b11000000000000 J
b110000000000000000000100010100 "
b110000000000000000000100010100 8
b11000000000000 C
b100010100 ?
0!
0-
#2000000
b110000000000000000000100010100 )
1!
1-
#2010000
0!
0-
#2020000
b100001101 .
1!
1-
#2030000
0!
0-
#2040000
b100010100 <
b100010100 @
b100010100 D
b100010100 H
b100010100 7
b100010100 %
1!
1-
#2050000
b1010 >
b0 B
b1010 F
b0 J
b1010 "
b1010 8
b1010 ?
b0 C
0!
0-
#2060000
b1001 +
1!
1-
#2070000
0!
0-
#2080000
b1001 >
b1001 F
b1001 "
b1001 8
b1001 0
0,
11
b1101 2
1!
1-
#2090000
0!
0-
#2100000
b1010 >
b0 B
b1010 F
b0 J
b1010 "
b1010 8
b100001101 <
b100001101 @
b100001101 D
b100001101 H
b100001101 7
1,
01
b100001101 %
1!
1-
#2110000
b100010100 >
b10000000000000 B
b100010100 F
b10000000000000 J
b100000000000000000000100010100 "
b100000000000000000000100010100 8
b10000000000000 C
b100010100 ?
0!
0-
#2120000
b100000000000000000000100010100 )
1!
1-
#2130000
0!
0-
#2140000
b100001110 .
1!
1-
#2150000
0!
0-
#2160000
b100010100 <
b100010100 @
b100010100 D
b100010100 H
b100010100 7
b100010100 %
1!
1-
#2170000
b1001 >
b0 B
b1001 F
b0 J
b1001 "
b1001 8
b1001 ?
b0 C
0!
0-
#2180000
1!
1-
#2190000
0!
0-
#2200000
b1110 2
1!
1-
#2210000
0!
0-
#2220000
b100001110 <
b100001110 @
b100001110 D
b100001110 H
b100001110 7
b100001110 %
1!
1-
#2230000
b10 >
b101000000000000 B
b10 F
b101000000000000 J
b1010000000000000000000000000010 "
b1010000000000000000000000000010 8
b101000000000000 C
b10 ?
0!
0-
#2240000
b1010000000000000000000000000010 )
1!
1-
#2250000
0!
0-
#2260000
b100001111 .
1!
1-
#2270000
0!
0-
#2280000
b1111 2
1!
1-
#2290000
0!
0-
#2300000
b100001111 <
b100001111 @
b100001111 D
b100001111 H
b100001111 7
b100001111 %
1!
1-
#2310000
b100000000 >
b110000000000000 B
b100000000 F
b110000000000000 J
b1100000000000000000000100000000 "
b1100000000000000000000100000000 8
b110000000000000 C
b100000000 ?
0!
0-
#2320000
b1100000000000000000000100000000 )
1!
1-
#2330000
0!
0-
#2340000
b100010000 .
1!
1-
#2350000
0!
0-
#2360000
b10000 2
1!
1-
#2370000
0!
0-
#2380000
b100010000 <
b100010000 @
b100010000 D
b100010000 H
b100010000 7
b100010000 %
1!
1-
#2390000
b0 >
b1000000000000 B
b0 F
b1000000000000 J
b10000000000000000000000000000 "
b10000000000000000000000000000 8
b1000000000000 C
b0 ?
0!
0-
#2400000
b10000000000000000000000000000 )
1!
1-
#2410000
0!
0-
#2420000
b100010001 .
1!
1-
#2430000
0!
0-
#2440000
b11111111 &
b10001 2
1!
1-
#2450000
0!
0-
#2460000
b100010001 <
b100010001 @
b100010001 D
b100010001 H
b100010001 7
b100010001 %
1!
1-
#2470000
b0 B
b0 J
b0 "
b0 8
b0 C
0!
0-
